agjax/__init__.py
agjax/py.typed
agjax/utils.py
agjax/wrapper.py
agjax/experimental/__init__.py
agjax/experimental/wrapper.py
agjax-0.3.7.dist-info/licenses/LICENSE
agjax-0.3.7.dist-info/METADATA
agjax-0.3.7.dist-info/WHEEL
agjax-0.3.7.dist-info/top_level.txt
agjax-0.3.7.dist-info/RECORD
