Metadata-Version: 2.4
Name: agjax
Version: 0.3.7
Summary: A jax wrapper for autograd-differentiable functions.
Author-email: "Martin F. Schubert" <mfschubert@gmail.com>
Maintainer-email: "Martin F. Schubert" <mfschubert@gmail.com>
License-Expression: MIT
Keywords: autograd,jax,python,wrapper,gradient
Requires-Python: >=3.7
License-File: LICENSE
Requires-Dist: autograd
Requires-Dist: jax>=0.4.27
Requires-Dist: jaxlib
Requires-Dist: numpy
Provides-Extra: tests
Requires-Dist: parameterized; extra == "tests"
Requires-Dist: pytest; extra == "tests"
Requires-Dist: pytest-cov; extra == "tests"
Requires-Dist: pytest-xdist; extra == "tests"
Provides-Extra: docs
Requires-Dist: matplotlib; extra == "docs"
Requires-Dist: jupyter-book==1.0.4.post1; extra == "docs"
Requires-Dist: sphinx-autodoc-typehints; extra == "docs"
Requires-Dist: sphinx-click; extra == "docs"
Requires-Dist: ceviche_challenges; extra == "docs"
Provides-Extra: dev
Requires-Dist: agjax[docs,tests]; extra == "dev"
Requires-Dist: bump-my-version; extra == "dev"
Requires-Dist: darglint; extra == "dev"
Requires-Dist: mypy; extra == "dev"
Requires-Dist: pre-commit; extra == "dev"
Dynamic: license-file
